MANIFEST.in
README.txt
setup.py
pyprocess/__init__.py
pyprocess/setProcess.py
pyprocess.egg-info/PKG-INFO
pyprocess.egg-info/SOURCES.txt
pyprocess.egg-info/dependency_links.txt
pyprocess.egg-info/requires.txt
pyprocess.egg-info/top_level.txt