Metadata-Version: 1.0
Name: pyprocess
Version: 0.0.3
Summary: process name managment.
Home-page: https://github.com/Nievous/pyprocess
Author: Daniel Mondaca
Author-email: dnielm@gmail.com
License: Bsd
Keywords: process name
Platform: GNU/Linux
Classifier: Development Status :: 4 - Beta
Classifier: Intended Audience :: Developers
Classifier: License :: OSI Approved :: BSD License
Classifier: Operating System :: POSIX :: Linux
Classifier: Programming Language :: Python
Classifier: Topic :: Software Development
